CHANGELOG
LICENSE
MANIFEST.in
README.rst
debug_cache.py
setup.py
debug_cache.egg-info/PKG-INFO
debug_cache.egg-info/SOURCES.txt
debug_cache.egg-info/dependency_links.txt
debug_cache.egg-info/pbr.json
debug_cache.egg-info/requires.txt
debug_cache.egg-info/top_level.txt